pyolaf/__init__.py
pyolaf/aliasing.py
pyolaf/fftpack.py
pyolaf/geometry.py
pyolaf/lf.py
pyolaf/project.py
pyolaf/transform.py
pyolaf-0.2.1.dist-info/LICENSE
pyolaf-0.2.1.dist-info/METADATA
pyolaf-0.2.1.dist-info/WHEEL
pyolaf-0.2.1.dist-info/top_level.txt
pyolaf-0.2.1.dist-info/RECORD
