Metadata-Version: 2.1
Name: pyolaf
Version: 0.2.1
Summary: 3D reconstruction framework for light field microscopy
Home-page: https://github.com/lambdaloop/pyolaf
Author: Lili Karashchuk
Author-email: krchtchk@gmail.com
Classifier: Programming Language :: Python :: 3
Classifier: License :: OSI Approved :: Apache Software License
Classifier: Intended Audience :: Science/Research
Classifier: Topic :: Scientific/Engineering
Classifier: Topic :: Scientific/Engineering :: Image Recognition
Classifier: Topic :: Scientific/Engineering :: Bio-Informatics
License-File: LICENSE
Requires-Dist: pyyaml
Requires-Dist: numpy
Requires-Dist: scipy
Requires-Dist: tqdm
Requires-Dist: tifffile
Requires-Dist: scikit-image
Requires-Dist: matplotlib
Provides-Extra: gpu
Requires-Dist: cupy ; extra == 'gpu'
